setup.py
pakiet_testowy/__init__.py
pakiet_testowy/dzialania.py
pogodabial.egg-info/PKG-INFO
pogodabial.egg-info/SOURCES.txt
pogodabial.egg-info/dependency_links.txt
pogodabial.egg-info/top_level.txt