Metadata-Version: 2.1
Name: pogodabial
Version: 1.0
Summary: Pakiet testowy
Home-page: http://sda.pl
License: UNKNOWN
Platform: UNKNOWN
